fermata/__init__.py
fermata/cli.py
fermata_edgedet_cli-0.1.dist-info/METADATA
fermata_edgedet_cli-0.1.dist-info/WHEEL
fermata_edgedet_cli-0.1.dist-info/entry_points.txt
fermata_edgedet_cli-0.1.dist-info/top_level.txt
fermata_edgedet_cli-0.1.dist-info/RECORD
