Metadata-Version: 2.1
Name: fermata-edgedet-cli
Version: 0.1
Summary: CLI tool for authenticating and calling the Fermata API
Home-page: https://github.com/dageorge1111/fermata-cli
Author: Daniel George
License: UNKNOWN
Platform: UNKNOWN
Classifier: Programming Language :: Python :: 3
Requires-Dist: Flask
Requires-Dist: requests
